odoo/addons/report_qweb_operating_unit/README.rst
odoo/addons/report_qweb_operating_unit/__init__.py
odoo/addons/report_qweb_operating_unit/__manifest__.py
odoo/addons/report_qweb_operating_unit/i18n/it.po
odoo/addons/report_qweb_operating_unit/i18n/pt.po
odoo/addons/report_qweb_operating_unit/i18n/report_qweb_operating_unit.pot
odoo/addons/report_qweb_operating_unit/readme/CONTRIBUTORS.rst
odoo/addons/report_qweb_operating_unit/readme/DESCRIPTION.rst
odoo/addons/report_qweb_operating_unit/static/description/icon.png
odoo/addons/report_qweb_operating_unit/static/description/index.html
odoo/addons/report_qweb_operating_unit/views/report_qweb_operating_unit.xml
odoo12_addon_report_qweb_operating_unit-12.0.1.0.0.99.dev12.dist-info/METADATA
odoo12_addon_report_qweb_operating_unit-12.0.1.0.0.99.dev12.dist-info/WHEEL
odoo12_addon_report_qweb_operating_unit-12.0.1.0.0.99.dev12.dist-info/top_level.txt
odoo12_addon_report_qweb_operating_unit-12.0.1.0.0.99.dev12.dist-info/RECORD
